[
  {
    "title": "Skyline Serenity Villa",
    "description": "An ultra-modern villa in JP Nagar featuring a rooftop pool, skylit atrium, and Italian marble interiors designed for elite comfort.",
    "price": 142000000,
    "address": "JP Nagar",
    "city": "Bengaluru",
    "country": "India",
    "image": "https://images.pexels.com/photos/7031406/pexels-photo-7031406.jpeg?auto=compress&cs=tinysrgb&w=1260&h=750&dpr=1",
    "facilities": { "bathrooms": 5, "parking": 3, "bedrooms": 6 },
    "userEmail": "nikhil.reddy@gmail.com",
    "createdAt": "2025-02-15T10:38:48.762Z",
    "updatedAt": "2025-02-15T10:38:48.762Z"
  },
  {
    "title": "Indiranagar Platinum Residency",
    "description": "A stunning architectural gem in Indiranagar with high ceilings, panoramic glass walls, and a private infinity-edge pool.",
    "price": 158000000,
    "address": "Indiranagar",
    "city": "Bengaluru",
    "country": "India",
    "image": "https://3.bp.blogspot.com/-84l-BoUL090/VTDHcQzSTNI/AAAAAAAAuHI/Khftta_CF5E/s1920/wow-home-design.jpg",
    "facilities": { "bathrooms": 6, "parking": 3, "bedrooms": 5 },
    "userEmail": "shruti.kapoor@gmail.com",
    "createdAt": "2025-05-10T15:12:19.231Z",
    "updatedAt": "2025-05-10T15:12:19.231Z"
  },
  {
    "title": "Whitefield Royal Estate",
    "description": "A majestic 7BHK estate with sprawling lawns, smart home systems, and an exclusive art-inspired interior in Whitefield.",
    "price": 169000000,
    "address": "Whitefield",
    "city": "Bengaluru",
    "country": "India",
    "image": "https://images.pexels.com/photos/323780/pexels-photo-323780.jpeg?auto=compress&cs=tinysrgb&w=1260&h=750&dpr=1",
    "facilities": { "bathrooms": 7, "parking": 4, "bedrooms": 7 },
    "userEmail": "karan.mehra@gmail.com",
    "createdAt": "2025-08-22T09:26:20.051Z",
    "updatedAt": "2025-08-22T09:26:20.051Z"
  },
  {
    "title": "The Green Horizon Villa",
    "description": "An eco-luxury villa surrounded by lush greens in Sarjapur Road, designed with solar tech and an open-air jacuzzi garden.",
    "price": 132000000,
    "address": "Sarjapur Road",
    "city": "Bengaluru",
    "country": "India",
    "image": "https://e0.pxfuel.com/wallpapers/12/377/desktop-wallpaper-beautiful-houses-beautiful-mansion.jpg",
    "facilities": { "bathrooms": 5, "parking": 2, "bedrooms": 5 },
    "userEmail": "aarti.nair@gmail.com",
    "createdAt": "2025-07-18T13:42:37.946Z",
    "updatedAt": "2025-07-18T13:42:37.946Z"
  },
  {
    "title": "The Oberon Mansion",
    "description": "A bold and timeless villa in Koramangala with grand marble halls, a theatre room, and European-style landscaped gardens.",
    "price": 155000000,
    "address": "Koramangala",
    "city": "Bengaluru",
    "country": "India",
    "image": "https://images.pexels.com/photos/208736/pexels-photo-208736.jpeg",
    "facilities": { "bathrooms": 8, "parking": 4, "bedrooms": 8 },
    "userEmail": "vishal.patel@gmail.com",
    "createdAt": "2025-09-09T10:39:35.044Z",
    "updatedAt": "2025-09-09T10:39:35.044Z"
  },
  {
    "title": "Prestige Palm Manor",
    "description": "A grand 5BHK mansion located in Yelahanka, offering premium finishes, private gardens, and panoramic balcony views.",
    "price": 149000000,
    "address": "Yelahanka",
    "city": "Bengaluru",
    "country": "India",
    "image": "https://www.hollywoodreporter.com/wp-content/uploads/2023/03/image_h_01-H-2023.jpg",
    "facilities": { "bathrooms": 6, "parking": 3, "bedrooms": 5 },
    "userEmail": "megha.r@gmail.com",
    "createdAt": "2026-01-21T11:41:54.156Z",
    "updatedAt": "2026-01-21T11:41:54.156Z"
  },
  {
    "title": "Palmcrest Elite Villa",
    "description": "A contemporary smart home in HSR Layout featuring rooftop gardens, skylights, and an automated lighting ecosystem.",
    "price": 168000000,
    "address": "HSR Layout",
    "city": "Bengaluru",
    "country": "India",
    "image": "https://st.hzcdn.com/simgs/pictures/exteriors/builders-in-kochi-creo-homes-pvt-ltd-img~a751d25e0d2ef808_4-0254-1-cb5c87b.jpg",
    "facilities": { "bathrooms": 5, "parking": 2, "bedrooms": 5 },
    "userEmail": "ravi.kumar@gmail.com",
    "createdAt": "2025-11-14T10:42:58.826Z",
    "updatedAt": "2025-11-14T10:42:58.826Z"
  },
  {
    "title": "Summerhill Estate",
    "description": "Located in Jayanagar, this luxurious home offers a blend of classic architecture with cutting-edge smart home features.",
    "price": 123000000,
    "address": "Jayanagar",
    "city": "Bengaluru",
    "country": "India",
    "image": "https://i.pinimg.com/originals/89/56/5c/89565c305737e1da2a1a5b62600fbcd4.jpg",
    "facilities": { "bathrooms": 4, "parking": 2, "bedrooms": 4 },
    "userEmail": "simran.arora@gmail.com",
    "createdAt": "2025-06-11T10:43:18.186Z",
    "updatedAt": "2025-06-11T10:43:18.186Z"
  },
  {
    "title": "Crimson Peak Chalet",
    "description": "Perched in the peaceful enclave of Electronic City, this 4BHK retreat exudes minimalistic design and natural light.",
    "price": 119000000,
    "address": "Electronic City",
    "city": "Bengaluru",
    "country": "India",
    "image": "https://cutewallpaper.org/24/house-images/1819611997.jpg",
    "facilities": { "bathrooms": 4, "parking": 2, "bedrooms": 4 },
    "userEmail": "arjun.desai@gmail.com",
    "createdAt": "2026-03-02T10:00:00.000Z",
    "updatedAt": "2026-03-02T10:00:00.000Z"
  }
]
